{
  "products": [
    {
      "id": "2",
      "code": "P002",
      "designation": "Produit 2",
      "prix": 100,
      "date_expiration": "2026-02-01",
      "description": "Deuxième produit"
    },
    {
      "id": 5,
      "code": "L0001",
      "designation": "LAIT",
      "prix": 100,
      "date_expiration": null,
      "description": null
    },
    {
      "id": 6,
      "code": "SU01",
      "designation": "SUCRE",
      "prix": 25,
      "date_expiration": null,
      "description": null
    },
    {
      "id": 7,
      "code": "V001",
      "designation": "VIANDE",
      "prix": 3000,
      "date_expiration": null,
      "description": null
    }
  ]
}